pyspike/DiscreteFunc.py
pyspike/PieceWiseConstFunc.py
pyspike/PieceWiseLinFunc.py
pyspike/SpikeTrain.py
pyspike/__init__.py
pyspike/generic.py
pyspike/isi_distance.py
pyspike/psth.py
pyspike/spike_directionality.py
pyspike/spike_distance.py
pyspike/spike_sync.py
pyspike/spikes.py
pyspike/cython/__init__.py
pyspike/cython/cython_add.c
pyspike/cython/cython_add.so
pyspike/cython/cython_directionality.c
pyspike/cython/cython_directionality.so
pyspike/cython/cython_distances.c
pyspike/cython/cython_distances.so
pyspike/cython/cython_profiles.c
pyspike/cython/cython_profiles.so
pyspike/cython/cython_simulated_annealing.c
pyspike/cython/cython_simulated_annealing.so
pyspike/cython/directionality_python_backend.py
pyspike/cython/python_backend.py
pyspike-0.7.0.dist-info/METADATA
pyspike-0.7.0.dist-info/WHEEL
pyspike-0.7.0.dist-info/top_level.txt
pyspike-0.7.0.dist-info/RECORD
