Metadata-Version: 2.1
Name: pyspike
Version: 0.7.0
Summary: A Python library for the numerical analysis of spiketrain similarity
Home-page: https://github.com/mariomulansky/PySpike
Author: Mario Mulansky
Author-email: mario.mulansky@gmx.net
License: BSD
Keywords: data analysis,spike,neuroscience
Platform: UNKNOWN
Classifier: Development Status :: 4 - Beta
Classifier: Intended Audience :: Science/Research
Classifier: Topic :: Scientific/Engineering
Classifier: Topic :: Scientific/Engineering :: Information Analysis
Classifier: License :: OSI Approved :: BSD License
Classifier: Programming Language :: Python :: 3
Classifier: Programming Language :: Python :: 3.7
Classifier: Programming Language :: Python :: 3.8
Classifier: Programming Language :: Python :: 3.9
Classifier: Programming Language :: Python :: 3.10
Requires-Dist: numpy
